{
    "5C:17:CF:0F:2B:73": {
        "2025-02-14": [
            {
                "time": "12:30:15.094971",
                "x": 204,
                "y": 323
            },
            {
                "time": "12:30:47.093533",
                "x": 206,
                "y": 321
            },
            {
                "time": "12:31:17.102980",
                "x": 206,
                "y": 321
            },
            {
                "time": "12:31:47.112358",
                "x": 206,
                "y": 321
            },
            {
                "time": "12:32:17.120749",
                "x": 206,
                "y": 321
            },
            {
                "time": "12:32:47.129737",
                "x": 259,
                "y": 347
            },
            {
                "time": "12:33:17.142225",
                "x": 293,
                "y": 320
            },
            {
                "time": "12:33:47.162291",
                "x": 307,
                "y": 309
            },
            {
                "time": "12:34:17.179811",
                "x": 402,
                "y": 254
            },
            {
                "time": "12:34:47.186862",
                "x": 402,
                "y": 254
            },
            {
                "time": "12:35:17.194523",
                "x": 402,
                "y": 254
            },
            {
                "time": "12:35:47.202602",
                "x": 402,
                "y": 254
            },
            {
                "time": "12:36:17.211609",
                "x": 402,
                "y": 254
            },
            {
                "time": "12:36:47.219399",
                "x": 355,
                "y": 287
            },
            {
                "time": "12:37:17.228205",
                "x": 383,
                "y": 269
            },
            {
                "time": "12:37:47.266480",
                "x": 383,
                "y": 240
            },
            {
                "time": "12:38:17.273869",
                "x": 359,
                "y": 223
            },
            {
                "time": "12:38:47.281705",
                "x": 359,
                "y": 223
            },
            {
                "time": "12:39:17.292956",
                "x": 359,
                "y": 223
            },
            {
                "time": "12:39:47.299071",
                "x": 359,
                "y": 223
            },
            {
                "time": "12:40:17.307228",
                "x": 359,
                "y": 223
            },
            {
                "time": "12:40:47.320722",
                "x": 359,
                "y": 223
            },
            {
                "time": "12:41:17.330112",
                "x": 359,
                "y": 223
            }
        ],
        "2025-02-21": [
            {
                "time": "11:47:18.009927",
                "x": 414,
                "y": 253
            },
            {
                "time": "11:47:48.019526",
                "x": 414,
                "y": 253
            },
            {
                "time": "11:48:18.027810",
                "x": 414,
                "y": 253
            },
            {
                "time": "11:48:48.037726",
                "x": 414,
                "y": 253
            },
            {
                "time": "11:49:18.050979",
                "x": 414,
                "y": 253
            },
            {
                "time": "11:49:48.061215",
                "x": 384,
                "y": 214
            },
            {
                "time": "11:50:18.068588",
                "x": 469,
                "y": 166
            },
            {
                "time": "11:50:48.076690",
                "x": 469,
                "y": 166
            },
            {
                "time": "11:51:18.084698",
                "x": 469,
                "y": 166
            },
            {
                "time": "11:51:48.094869",
                "x": 469,
                "y": 166
            },
            {
                "time": "11:52:18.103371",
                "x": 469,
                "y": 166
            },
            {
                "time": "11:52:48.113902",
                "x": 469,
                "y": 166
            },
            {
                "time": "11:53:18.123087",
                "x": 469,
                "y": 166
            },
            {
                "time": "11:53:48.137842",
                "x": 513,
                "y": 213
            },
            {
                "time": "11:54:20.196906",
                "x": 513,
                "y": 213
            },
            {
                "time": "11:54:39.635820",
                "x": 469,
                "y": 141
            },
            {
                "time": "11:55:09.646324",
                "x": 469,
                "y": 141
            },
            {
                "time": "11:55:39.654626",
                "x": 355,
                "y": 206
            },
            {
                "time": "11:56:09.662197",
                "x": 355,
                "y": 206
            },
            {
                "time": "11:56:39.671727",
                "x": 329,
                "y": 220
            },
            {
                "time": "11:57:09.682101",
                "x": 329,
                "y": 220
            },
            {
                "time": "11:57:39.700340",
                "x": 300,
                "y": 205
            },
            {
                "time": "11:58:09.707273",
                "x": 286,
                "y": 213
            },
            {
                "time": "11:58:39.721897",
                "x": 240,
                "y": 223
            },
            {
                "time": "11:59:09.732638",
                "x": 240,
                "y": 223
            },
            {
                "time": "11:59:39.741418",
                "x": 240,
                "y": 223
            },
            {
                "time": "12:00:09.756893",
                "x": 227,
                "y": 200
            },
            {
                "time": "12:00:39.765389",
                "x": 221,
                "y": 203
            },
            {
                "time": "12:01:09.792544",
                "x": 221,
                "y": 206
            },
            {
                "time": "12:01:39.805288",
                "x": 240,
                "y": 229
            },
            {
                "time": "12:02:09.817671",
                "x": 240,
                "y": 229
            },
            {
                "time": "12:02:39.822537",
                "x": 240,
                "y": 229
            },
            {
                "time": "12:03:09.833389",
                "x": 240,
                "y": 229
            },
            {
                "time": "12:03:39.840473",
                "x": 240,
                "y": 229
            },
            {
                "time": "12:04:09.850973",
                "x": 240,
                "y": 229
            },
            {
                "time": "12:04:39.861431",
                "x": 240,
                "y": 229
            },
            {
                "time": "12:05:09.869174",
                "x": 240,
                "y": 229
            },
            {
                "time": "12:05:39.878008",
                "x": 240,
                "y": 229
            },
            {
                "time": "12:06:09.886171",
                "x": 240,
                "y": 229
            },
            {
                "time": "12:06:39.896993",
                "x": 240,
                "y": 229
            },
            {
                "time": "12:07:09.905066",
                "x": 240,
                "y": 229
            },
            {
                "time": "12:07:39.914650",
                "x": 240,
                "y": 229
            },
            {
                "time": "12:08:09.925216",
                "x": 240,
                "y": 229
            },
            {
                "time": "12:08:39.932371",
                "x": 240,
                "y": 229
            },
            {
                "time": "12:09:09.942845",
                "x": 240,
                "y": 229
            },
            {
                "time": "12:09:39.950472",
                "x": 240,
                "y": 229
            },
            {
                "time": "12:10:09.961216",
                "x": 240,
                "y": 229
            },
            {
                "time": "12:10:39.970933",
                "x": 240,
                "y": 229
            },
            {
                "time": "12:11:09.979567",
                "x": 240,
                "y": 229
            },
            {
                "time": "12:11:39.988050",
                "x": 240,
                "y": 229
            },
            {
                "time": "12:12:09.996046",
                "x": 240,
                "y": 229
            },
            {
                "time": "12:12:40.004401",
                "x": 240,
                "y": 229
            },
            {
                "time": "12:13:10.012515",
                "x": 240,
                "y": 229
            },
            {
                "time": "12:13:40.021239",
                "x": 240,
                "y": 229
            },
            {
                "time": "12:14:10.030337",
                "x": 240,
                "y": 229
            },
            {
                "time": "12:14:40.042750",
                "x": 240,
                "y": 229
            },
            {
                "time": "12:15:10.049838",
                "x": 240,
                "y": 229
            },
            {
                "time": "12:15:40.058122",
                "x": 240,
                "y": 229
            },
            {
                "time": "12:16:10.066650",
                "x": 240,
                "y": 229
            },
            {
                "time": "12:16:40.075167",
                "x": 240,
                "y": 229
            },
            {
                "time": "12:17:10.084119",
                "x": 240,
                "y": 229
            },
            {
                "time": "12:17:40.097084",
                "x": 240,
                "y": 229
            },
            {
                "time": "12:18:10.102208",
                "x": 240,
                "y": 229
            },
            {
                "time": "12:18:40.112859",
                "x": 240,
                "y": 229
            },
            {
                "time": "12:19:10.122288",
                "x": 240,
                "y": 229
            },
            {
                "time": "12:19:40.131720",
                "x": 240,
                "y": 229
            },
            {
                "time": "12:20:10.139145",
                "x": 240,
                "y": 229
            },
            {
                "time": "12:20:40.147167",
                "x": 240,
                "y": 229
            },
            {
                "time": "12:21:10.157959",
                "x": 240,
                "y": 229
            },
            {
                "time": "12:21:40.165622",
                "x": 240,
                "y": 229
            },
            {
                "time": "12:22:10.174298",
                "x": 240,
                "y": 229
            },
            {
                "time": "12:22:40.183885",
                "x": 240,
                "y": 229
            },
            {
                "time": "12:23:10.193860",
                "x": 240,
                "y": 229
            },
            {
                "time": "12:23:40.203979",
                "x": 240,
                "y": 229
            },
            {
                "time": "12:24:10.213681",
                "x": 240,
                "y": 229
            },
            {
                "time": "12:24:40.222267",
                "x": 240,
                "y": 229
            },
            {
                "time": "12:25:10.233126",
                "x": 240,
                "y": 229
            },
            {
                "time": "12:25:40.245206",
                "x": 240,
                "y": 229
            },
            {
                "time": "12:26:10.255185",
                "x": 240,
                "y": 229
            },
            {
                "time": "12:26:40.264881",
                "x": 240,
                "y": 229
            },
            {
                "time": "12:27:10.271740",
                "x": 240,
                "y": 229
            },
            {
                "time": "12:27:40.280745",
                "x": 240,
                "y": 229
            },
            {
                "time": "12:28:10.290203",
                "x": 240,
                "y": 229
            },
            {
                "time": "12:28:40.301235",
                "x": 240,
                "y": 229
            },
            {
                "time": "12:29:10.310145",
                "x": 240,
                "y": 229
            },
            {
                "time": "12:29:40.319338",
                "x": 240,
                "y": 229
            },
            {
                "time": "12:30:10.330249",
                "x": 240,
                "y": 229
            },
            {
                "time": "12:30:40.340414",
                "x": 240,
                "y": 229
            },
            {
                "time": "12:31:10.348212",
                "x": 240,
                "y": 229
            },
            {
                "time": "12:31:40.358337",
                "x": 240,
                "y": 229
            },
            {
                "time": "12:32:10.366585",
                "x": 240,
                "y": 229
            },
            {
                "time": "12:32:40.376687",
                "x": 240,
                "y": 229
            },
            {
                "time": "12:33:10.386251",
                "x": 240,
                "y": 229
            },
            {
                "time": "12:33:40.395216",
                "x": 240,
                "y": 229
            },
            {
                "time": "12:34:10.402170",
                "x": 240,
                "y": 229
            }
        ],
        "2025-02-27": [
            {
                "time": "22:34:37.676503",
                "x": 240,
                "y": 229
            },
            {
                "time": "22:35:07.686329",
                "x": 240,
                "y": 225
            },
            {
                "time": "22:35:37.696692",
                "x": 269,
                "y": 248
            },
            {
                "time": "22:36:07.702465",
                "x": 269,
                "y": 248
            },
            {
                "time": "22:36:37.712050",
                "x": 269,
                "y": 248
            },
            {
                "time": "22:37:07.719825",
                "x": 269,
                "y": 248
            },
            {
                "time": "22:37:37.727074",
                "x": 269,
                "y": 248
            },
            {
                "time": "22:38:07.737018",
                "x": 269,
                "y": 248
            },
            {
                "time": "22:38:37.744273",
                "x": 269,
                "y": 248
            },
            {
                "time": "22:39:07.753961",
                "x": 269,
                "y": 248
            },
            {
                "time": "22:59:47.097315",
                "x": 258,
                "y": 271
            },
            {
                "time": "23:00:17.103666",
                "x": 258,
                "y": 271
            },
            {
                "time": "23:00:47.111959",
                "x": 258,
                "y": 271
            },
            {
                "time": "23:01:17.120187",
                "x": 258,
                "y": 271
            },
            {
                "time": "23:01:47.128760",
                "x": 258,
                "y": 271
            },
            {
                "time": "23:02:17.137614",
                "x": 258,
                "y": 271
            },
            {
                "time": "23:02:47.148480",
                "x": 258,
                "y": 271
            },
            {
                "time": "23:03:17.156856",
                "x": 258,
                "y": 271
            },
            {
                "time": "23:03:56.168451",
                "x": 258,
                "y": 271
            },
            {
                "time": "23:04:26.176767",
                "x": 258,
                "y": 271
            },
            {
                "time": "23:04:56.184100",
                "x": 258,
                "y": 271
            },
            {
                "time": "23:05:26.193289",
                "x": 258,
                "y": 271
            },
            {
                "time": "23:05:56.201155",
                "x": 258,
                "y": 271
            },
            {
                "time": "23:06:26.209028",
                "x": 258,
                "y": 271
            },
            {
                "time": "23:06:56.218890",
                "x": 258,
                "y": 271
            },
            {
                "time": "23:07:26.227628",
                "x": 258,
                "y": 271
            },
            {
                "time": "23:07:56.235666",
                "x": 258,
                "y": 271
            },
            {
                "time": "23:08:26.244693",
                "x": 258,
                "y": 271
            },
            {
                "time": "23:08:56.251974",
                "x": 258,
                "y": 271
            },
            {
                "time": "23:09:26.261021",
                "x": 258,
                "y": 271
            },
            {
                "time": "23:09:56.268368",
                "x": 258,
                "y": 271
            },
            {
                "time": "23:10:26.277005",
                "x": 258,
                "y": 271
            },
            {
                "time": "23:10:56.285896",
                "x": 258,
                "y": 271
            },
            {
                "time": "23:11:26.293126",
                "x": 258,
                "y": 271
            },
            {
                "time": "23:11:56.301929",
                "x": 258,
                "y": 271
            },
            {
                "time": "23:12:26.308508",
                "x": 258,
                "y": 271
            },
            {
                "time": "23:12:56.316992",
                "x": 258,
                "y": 271
            },
            {
                "time": "23:13:26.325151",
                "x": 258,
                "y": 271
            },
            {
                "time": "23:13:56.334195",
                "x": 258,
                "y": 271
            },
            {
                "time": "23:14:26.342898",
                "x": 258,
                "y": 271
            },
            {
                "time": "23:14:56.349834",
                "x": 258,
                "y": 271
            },
            {
                "time": "23:15:26.358375",
                "x": 258,
                "y": 271
            },
            {
                "time": "23:15:56.366501",
                "x": 258,
                "y": 271
            },
            {
                "time": "23:16:26.374823",
                "x": 258,
                "y": 271
            },
            {
                "time": "23:16:56.383251",
                "x": 258,
                "y": 271
            },
            {
                "time": "23:17:26.391811",
                "x": 258,
                "y": 271
            },
            {
                "time": "23:17:56.400846",
                "x": 258,
                "y": 271
            },
            {
                "time": "23:18:26.408930",
                "x": 258,
                "y": 271
            },
            {
                "time": "23:18:56.416828",
                "x": 258,
                "y": 271
            },
            {
                "time": "23:19:26.425432",
                "x": 258,
                "y": 271
            },
            {
                "time": "23:19:56.432917",
                "x": 258,
                "y": 271
            },
            {
                "time": "23:20:26.442508",
                "x": 258,
                "y": 271
            },
            {
                "time": "23:28:23.641199",
                "x": 258,
                "y": 271
            },
            {
                "time": "23:28:53.650108",
                "x": 258,
                "y": 271
            },
            {
                "time": "23:29:23.657565",
                "x": 258,
                "y": 271
            },
            {
                "time": "23:29:53.665861",
                "x": 258,
                "y": 271
            },
            {
                "time": "23:30:23.673285",
                "x": 258,
                "y": 271
            },
            {
                "time": "23:30:53.681450",
                "x": 258,
                "y": 271
            },
            {
                "time": "23:31:23.692002",
                "x": 258,
                "y": 271
            },
            {
                "time": "23:31:53.699199",
                "x": 258,
                "y": 271
            },
            {
                "time": "23:32:23.707847",
                "x": 258,
                "y": 271
            },
            {
                "time": "23:32:53.715287",
                "x": 258,
                "y": 271
            },
            {
                "time": "23:33:23.721590",
                "x": 258,
                "y": 271
            },
            {
                "time": "23:33:53.730610",
                "x": 258,
                "y": 271
            },
            {
                "time": "23:34:23.738305",
                "x": 258,
                "y": 271
            },
            {
                "time": "23:34:53.747017",
                "x": 258,
                "y": 271
            },
            {
                "time": "23:35:23.755119",
                "x": 258,
                "y": 271
            },
            {
                "time": "23:35:53.763679",
                "x": 258,
                "y": 271
            },
            {
                "time": "23:36:23.772560",
                "x": 258,
                "y": 271
            },
            {
                "time": "23:36:53.779984",
                "x": 258,
                "y": 271
            },
            {
                "time": "23:37:23.788202",
                "x": 258,
                "y": 271
            },
            {
                "time": "23:37:53.796827",
                "x": 258,
                "y": 271
            },
            {
                "time": "23:38:23.805137",
                "x": 258,
                "y": 271
            },
            {
                "time": "23:38:53.813790",
                "x": 258,
                "y": 271
            },
            {
                "time": "23:39:23.821736",
                "x": 258,
                "y": 271
            },
            {
                "time": "23:39:53.829974",
                "x": 258,
                "y": 271
            },
            {
                "time": "23:40:23.838812",
                "x": 258,
                "y": 271
            },
            {
                "time": "23:40:53.847573",
                "x": 258,
                "y": 271
            },
            {
                "time": "23:41:23.855882",
                "x": 258,
                "y": 271
            },
            {
                "time": "23:41:53.863813",
                "x": 258,
                "y": 271
            },
            {
                "time": "23:42:23.872014",
                "x": 258,
                "y": 271
            },
            {
                "time": "23:42:53.881253",
                "x": 258,
                "y": 271
            },
            {
                "time": "23:43:23.890347",
                "x": 258,
                "y": 271
            },
            {
                "time": "23:43:53.898210",
                "x": 258,
                "y": 271
            },
            {
                "time": "23:44:23.906300",
                "x": 258,
                "y": 271
            },
            {
                "time": "23:44:53.916126",
                "x": 258,
                "y": 271
            },
            {
                "time": "23:45:23.923483",
                "x": 258,
                "y": 271
            },
            {
                "time": "23:45:53.931710",
                "x": 258,
                "y": 271
            },
            {
                "time": "23:46:23.940448",
                "x": 258,
                "y": 271
            },
            {
                "time": "23:46:53.947505",
                "x": 258,
                "y": 271
            },
            {
                "time": "23:47:23.955181",
                "x": 258,
                "y": 271
            },
            {
                "time": "23:47:53.963174",
                "x": 258,
                "y": 271
            },
            {
                "time": "23:48:23.971419",
                "x": 258,
                "y": 271
            },
            {
                "time": "23:48:53.979905",
                "x": 258,
                "y": 271
            },
            {
                "time": "23:49:23.991846",
                "x": 258,
                "y": 271
            },
            {
                "time": "23:49:53.999959",
                "x": 258,
                "y": 271
            },
            {
                "time": "23:50:24.008188",
                "x": 258,
                "y": 271
            },
            {
                "time": "23:50:54.017644",
                "x": 258,
                "y": 271
            },
            {
                "time": "23:51:24.025027",
                "x": 258,
                "y": 271
            },
            {
                "time": "23:51:54.034533",
                "x": 258,
                "y": 271
            },
            {
                "time": "23:52:24.042526",
                "x": 258,
                "y": 271
            },
            {
                "time": "23:52:54.051246",
                "x": 258,
                "y": 271
            },
            {
                "time": "23:53:24.059307",
                "x": 258,
                "y": 271
            },
            {
                "time": "23:53:54.067917",
                "x": 258,
                "y": 271
            },
            {
                "time": "23:54:24.076826",
                "x": 258,
                "y": 271
            },
            {
                "time": "23:54:54.086779",
                "x": 258,
                "y": 271
            }
        ],
        "2025-02-28": [
            {
                "time": "00:06:39.278137",
                "x": 258,
                "y": 271
            },
            {
                "time": "00:07:09.286655",
                "x": 258,
                "y": 271
            },
            {
                "time": "00:07:39.294320",
                "x": 258,
                "y": 271
            },
            {
                "time": "00:08:09.301911",
                "x": 258,
                "y": 271
            },
            {
                "time": "00:08:39.310396",
                "x": 258,
                "y": 271
            },
            {
                "time": "00:09:09.318625",
                "x": 258,
                "y": 271
            },
            {
                "time": "00:09:39.327282",
                "x": 258,
                "y": 271
            },
            {
                "time": "00:10:09.338035",
                "x": 258,
                "y": 271
            },
            {
                "time": "00:10:39.345045",
                "x": 258,
                "y": 271
            },
            {
                "time": "00:12:24.375842",
                "x": 258,
                "y": 271
            },
            {
                "time": "00:12:54.383879",
                "x": 258,
                "y": 271
            },
            {
                "time": "00:13:24.393875",
                "x": 258,
                "y": 271
            },
            {
                "time": "00:13:54.403255",
                "x": 258,
                "y": 271
            },
            {
                "time": "00:14:24.412528",
                "x": 258,
                "y": 271
            },
            {
                "time": "00:14:54.421174",
                "x": 258,
                "y": 271
            },
            {
                "time": "00:15:24.430447",
                "x": 258,
                "y": 271
            },
            {
                "time": "00:15:54.440615",
                "x": 258,
                "y": 271
            },
            {
                "time": "00:16:24.449940",
                "x": 258,
                "y": 271
            },
            {
                "time": "00:16:54.458813",
                "x": 258,
                "y": 271
            },
            {
                "time": "00:17:24.468197",
                "x": 258,
                "y": 271
            },
            {
                "time": "00:17:54.483882",
                "x": 258,
                "y": 271
            },
            {
                "time": "00:18:24.487802",
                "x": 258,
                "y": 271
            },
            {
                "time": "00:18:54.496174",
                "x": 258,
                "y": 271
            },
            {
                "time": "00:19:24.505754",
                "x": 258,
                "y": 271
            },
            {
                "time": "00:19:38.509436",
                "x": 345,
                "y": 370
            },
            {
                "time": "00:20:08.518989",
                "x": 345,
                "y": 370
            },
            {
                "time": "00:20:38.530109",
                "x": 345,
                "y": 370
            },
            {
                "time": "00:21:08.536292",
                "x": 345,
                "y": 370
            },
            {
                "time": "00:21:38.544009",
                "x": 345,
                "y": 370
            },
            {
                "time": "00:22:08.552591",
                "x": 345,
                "y": 370
            },
            {
                "time": "00:22:38.562747",
                "x": 345,
                "y": 370
            },
            {
                "time": "00:23:08.574790",
                "x": 345,
                "y": 370
            },
            {
                "time": "00:23:38.583563",
                "x": 345,
                "y": 370
            },
            {
                "time": "00:24:08.594057",
                "x": 345,
                "y": 370
            },
            {
                "time": "00:24:38.602853",
                "x": 345,
                "y": 370
            },
            {
                "time": "00:25:08.612303",
                "x": 345,
                "y": 370
            },
            {
                "time": "00:25:38.620719",
                "x": 345,
                "y": 370
            },
            {
                "time": "00:26:08.631059",
                "x": 345,
                "y": 370
            },
            {
                "time": "00:26:38.640499",
                "x": 345,
                "y": 370
            },
            {
                "time": "00:27:08.651651",
                "x": 345,
                "y": 370
            },
            {
                "time": "00:27:38.661496",
                "x": 345,
                "y": 370
            },
            {
                "time": "00:28:08.670494",
                "x": 345,
                "y": 370
            },
            {
                "time": "00:28:38.680704",
                "x": 345,
                "y": 370
            },
            {
                "time": "00:29:08.690077",
                "x": 345,
                "y": 370
            },
            {
                "time": "00:29:38.697308",
                "x": 345,
                "y": 370
            },
            {
                "time": "00:30:08.705977",
                "x": 345,
                "y": 370
            },
            {
                "time": "00:32:33.749271",
                "x": 258,
                "y": 271
            },
            {
                "time": "00:33:03.756871",
                "x": 258,
                "y": 271
            },
            {
                "time": "00:33:33.763519",
                "x": 258,
                "y": 271
            },
            {
                "time": "00:34:03.774060",
                "x": 258,
                "y": 271
            },
            {
                "time": "00:37:38.700047",
                "x": 381,
                "y": 242
            },
            {
                "time": "00:38:08.706387",
                "x": 381,
                "y": 242
            },
            {
                "time": "00:42:39.954053",
                "x": 258,
                "y": 271
            },
            {
                "time": "00:43:09.961680",
                "x": 258,
                "y": 271
            },
            {
                "time": "00:49:52.073344",
                "x": 258,
                "y": 271
            },
            {
                "time": "00:50:22.081937",
                "x": 258,
                "y": 271
            },
            {
                "time": "00:50:52.090543",
                "x": 258,
                "y": 271
            },
            {
                "time": "00:51:22.103815",
                "x": 258,
                "y": 271
            },
            {
                "time": "00:51:52.109709",
                "x": 258,
                "y": 271
            },
            {
                "time": "00:52:22.118044",
                "x": 258,
                "y": 271
            },
            {
                "time": "00:52:52.126791",
                "x": 258,
                "y": 271
            },
            {
                "time": "00:53:22.137417",
                "x": 258,
                "y": 271
            },
            {
                "time": "00:53:52.145809",
                "x": 258,
                "y": 271
            },
            {
                "time": "00:54:22.155388",
                "x": 258,
                "y": 271
            },
            {
                "time": "00:54:52.165848",
                "x": 258,
                "y": 271
            },
            {
                "time": "00:55:22.173147",
                "x": 258,
                "y": 271
            },
            {
                "time": "00:55:52.183393",
                "x": 258,
                "y": 271
            },
            {
                "time": "00:56:22.192498",
                "x": 258,
                "y": 271
            },
            {
                "time": "00:56:52.204675",
                "x": 258,
                "y": 271
            },
            {
                "time": "00:57:22.213424",
                "x": 258,
                "y": 271
            },
            {
                "time": "00:57:52.223019",
                "x": 258,
                "y": 271
            },
            {
                "time": "00:58:22.232666",
                "x": 258,
                "y": 271
            },
            {
                "time": "00:58:52.240199",
                "x": 258,
                "y": 271
            },
            {
                "time": "00:59:22.248856",
                "x": 258,
                "y": 271
            },
            {
                "time": "00:59:52.257982",
                "x": 258,
                "y": 271
            },
            {
                "time": "01:00:22.265940",
                "x": 258,
                "y": 271
            },
            {
                "time": "01:00:52.273315",
                "x": 258,
                "y": 271
            },
            {
                "time": "01:01:22.281527",
                "x": 258,
                "y": 271
            },
            {
                "time": "01:01:52.290090",
                "x": 258,
                "y": 271
            },
            {
                "time": "01:02:22.298664",
                "x": 258,
                "y": 271
            },
            {
                "time": "01:10:57.405874",
                "x": 345,
                "y": 370
            },
            {
                "time": "01:11:27.413434",
                "x": 345,
                "y": 370
            },
            {
                "time": "01:11:57.423037",
                "x": 345,
                "y": 370
            },
            {
                "time": "01:12:27.431014",
                "x": 345,
                "y": 370
            },
            {
                "time": "01:12:57.439231",
                "x": 345,
                "y": 370
            },
            {
                "time": "01:13:27.447955",
                "x": 345,
                "y": 370
            },
            {
                "time": "01:13:57.456309",
                "x": 345,
                "y": 370
            },
            {
                "time": "01:14:55.897821",
                "x": 258,
                "y": 271
            },
            {
                "time": "01:15:27.358110",
                "x": 258,
                "y": 271
            },
            {
                "time": "01:15:57.367599",
                "x": 258,
                "y": 271
            },
            {
                "time": "01:16:36.501055",
                "x": 345,
                "y": 370
            },
            {
                "time": "01:17:06.511208",
                "x": 345,
                "y": 370
            },
            {
                "time": "01:17:36.518420",
                "x": 345,
                "y": 370
            },
            {
                "time": "01:19:30.550116",
                "x": 345,
                "y": 370
            },
            {
                "time": "01:20:04.601274",
                "x": 258,
                "y": 271
            },
            {
                "time": "01:20:34.610716",
                "x": 258,
                "y": 271
            },
            {
                "time": "01:21:04.621025",
                "x": 258,
                "y": 271
            },
            {
                "time": "01:21:34.629901",
                "x": 258,
                "y": 271
            },
            {
                "time": "01:22:04.636523",
                "x": 258,
                "y": 271
            },
            {
                "time": "01:22:34.644873",
                "x": 258,
                "y": 271
            },
            {
                "time": "01:23:12.614137",
                "x": 345,
                "y": 370
            },
            {
                "time": "01:23:55.666968",
                "x": 258,
                "y": 271
            },
            {
                "time": "01:24:25.673712",
                "x": 258,
                "y": 271
            },
            {
                "time": "01:24:55.682259",
                "x": 258,
                "y": 271
            },
            {
                "time": "01:25:25.693814",
                "x": 258,
                "y": 271
            },
            {
                "time": "01:25:55.699909",
                "x": 258,
                "y": 271
            },
            {
                "time": "01:26:25.709323",
                "x": 258,
                "y": 271
            },
            {
                "time": "01:26:43.713379",
                "x": 258,
                "y": 271
            },
            {
                "time": "01:27:13.721661",
                "x": 258,
                "y": 271
            },
            {
                "time": "01:30:36.739300",
                "x": 345,
                "y": 370
            },
            {
                "time": "11:44:01.828829",
                "x": 381,
                "y": 242
            },
            {
                "time": "11:44:31.837709",
                "x": 381,
                "y": 242
            },
            {
                "time": "11:45:01.848884",
                "x": 381,
                "y": 242
            },
            {
                "time": "11:45:31.855290",
                "x": 381,
                "y": 242
            },
            {
                "time": "11:46:01.863725",
                "x": 381,
                "y": 242
            },
            {
                "time": "11:56:39.591372",
                "x": 258,
                "y": 271
            },
            {
                "time": "11:57:11.060893",
                "x": 258,
                "y": 271
            },
            {
                "time": "11:57:41.067859",
                "x": 258,
                "y": 271
            },
            {
                "time": "11:58:11.079423",
                "x": 258,
                "y": 271
            },
            {
                "time": "11:58:41.087115",
                "x": 258,
                "y": 271
            },
            {
                "time": "11:59:11.097380",
                "x": 258,
                "y": 271
            },
            {
                "time": "11:59:41.105703",
                "x": 258,
                "y": 271
            },
            {
                "time": "12:00:11.115981",
                "x": 258,
                "y": 271
            },
            {
                "time": "12:00:41.125140",
                "x": 258,
                "y": 271
            },
            {
                "time": "12:01:11.134355",
                "x": 258,
                "y": 271
            },
            {
                "time": "12:01:41.143457",
                "x": 258,
                "y": 271
            },
            {
                "time": "12:02:11.152913",
                "x": 258,
                "y": 271
            },
            {
                "time": "12:02:41.160724",
                "x": 258,
                "y": 271
            },
            {
                "time": "12:03:11.170704",
                "x": 258,
                "y": 271
            },
            {
                "time": "12:03:41.182860",
                "x": 258,
                "y": 271
            },
            {
                "time": "12:04:11.189704",
                "x": 258,
                "y": 271
            },
            {
                "time": "12:04:41.199240",
                "x": 258,
                "y": 271
            },
            {
                "time": "12:05:11.206756",
                "x": 258,
                "y": 271
            },
            {
                "time": "12:05:41.214538",
                "x": 258,
                "y": 271
            },
            {
                "time": "12:06:11.222392",
                "x": 258,
                "y": 271
            },
            {
                "time": "12:06:41.232927",
                "x": 258,
                "y": 271
            },
            {
                "time": "12:07:11.240559",
                "x": 258,
                "y": 271
            },
            {
                "time": "12:07:41.249103",
                "x": 258,
                "y": 271
            },
            {
                "time": "12:08:11.257671",
                "x": 258,
                "y": 271
            },
            {
                "time": "12:08:41.269540",
                "x": 258,
                "y": 271
            },
            {
                "time": "12:09:03.455074",
                "x": 258,
                "y": 271
            },
            {
                "time": "12:09:33.464133",
                "x": 258,
                "y": 271
            },
            {
                "time": "12:13:08.464538",
                "x": 345,
                "y": 370
            },
            {
                "time": "12:13:38.474313",
                "x": 345,
                "y": 370
            },
            {
                "time": "12:14:08.482502",
                "x": 345,
                "y": 370
            },
            {
                "time": "12:14:38.491903",
                "x": 345,
                "y": 370
            },
            {
                "time": "12:15:08.501778",
                "x": 345,
                "y": 370
            },
            {
                "time": "12:16:35.401912",
                "x": 381,
                "y": 242
            },
            {
                "time": "12:17:05.410692",
                "x": 381,
                "y": 242
            },
            {
                "time": "12:17:35.421343",
                "x": 381,
                "y": 242
            },
            {
                "time": "12:18:05.428016",
                "x": 381,
                "y": 242
            },
            {
                "time": "12:18:51.627742",
                "x": 258,
                "y": 271
            },
            {
                "time": "12:19:21.636752",
                "x": 258,
                "y": 271
            },
            {
                "time": "12:19:51.648098",
                "x": 258,
                "y": 271
            },
            {
                "time": "12:20:21.655666",
                "x": 258,
                "y": 271
            },
            {
                "time": "12:20:40.005311",
                "x": 258,
                "y": 271
            },
            {
                "time": "12:21:11.483519",
                "x": 258,
                "y": 271
            },
            {
                "time": "12:22:51.698789",
                "x": 258,
                "y": 271
            },
            {
                "time": "12:23:12.704134",
                "x": 258,
                "y": 271
            },
            {
                "time": "12:23:39.710639",
                "x": 258,
                "y": 271
            },
            {
                "time": "12:24:11.649674",
                "x": 345,
                "y": 370
            },
            {
                "time": "12:24:44.658005",
                "x": 345,
                "y": 370
            },
            {
                "time": "12:25:23.670541",
                "x": 345,
                "y": 370
            },
            {
                "time": "12:25:53.677247",
                "x": 345,
                "y": 370
            },
            {
                "time": "12:26:23.687214",
                "x": 345,
                "y": 370
            },
            {
                "time": "12:34:44.825431",
                "x": 345,
                "y": 370
            },
            {
                "time": "12:35:14.832465",
                "x": 345,
                "y": 370
            },
            {
                "time": "12:35:44.842556",
                "x": 345,
                "y": 370
            },
            {
                "time": "12:36:14.853192",
                "x": 345,
                "y": 370
            },
            {
                "time": "12:36:44.860723",
                "x": 345,
                "y": 370
            },
            {
                "time": "12:37:27.948214",
                "x": 258,
                "y": 271
            },
            {
                "time": "12:38:38.890678",
                "x": 345,
                "y": 370
            },
            {
                "time": "12:39:49.330144",
                "x": 258,
                "y": 271
            },
            {
                "time": "12:40:20.801367",
                "x": 258,
                "y": 271
            },
            {
                "time": "12:40:50.808949",
                "x": 258,
                "y": 271
            },
            {
                "time": "12:41:20.817999",
                "x": 258,
                "y": 271
            },
            {
                "time": "12:41:58.022566",
                "x": 258,
                "y": 271
            }
        ]
    },
    "4C:3B:2F:93:99:96": {
        "2025-02-14": [
            {
                "time": "12:30:15.095971",
                "x": 272,
                "y": 222
            },
            {
                "time": "12:30:47.093533",
                "x": 260,
                "y": 229
            },
            {
                "time": "12:31:17.103975",
                "x": 260,
                "y": 229
            },
            {
                "time": "12:31:47.112358",
                "x": 260,
                "y": 229
            },
            {
                "time": "12:32:17.120749",
                "x": 260,
                "y": 229
            },
            {
                "time": "12:32:47.129737",
                "x": 260,
                "y": 229
            },
            {
                "time": "12:33:17.143227",
                "x": 260,
                "y": 229
            },
            {
                "time": "12:33:47.162291",
                "x": 288,
                "y": 242
            },
            {
                "time": "12:34:17.180810",
                "x": 294,
                "y": 335
            },
            {
                "time": "12:34:47.187384",
                "x": 294,
                "y": 335
            },
            {
                "time": "12:35:17.195523",
                "x": 294,
                "y": 335
            },
            {
                "time": "12:35:47.203603",
                "x": 294,
                "y": 335
            },
            {
                "time": "12:36:17.212609",
                "x": 294,
                "y": 335
            },
            {
                "time": "12:36:47.219399",
                "x": 291,
                "y": 342
            },
            {
                "time": "12:37:17.229205",
                "x": 291,
                "y": 342
            },
            {
                "time": "12:37:47.268476",
                "x": 331,
                "y": 228
            },
            {
                "time": "12:38:17.273869",
                "x": 276,
                "y": 190
            },
            {
                "time": "12:38:47.282702",
                "x": 276,
                "y": 190
            },
            {
                "time": "12:39:17.295962",
                "x": 276,
                "y": 190
            },
            {
                "time": "12:39:47.300073",
                "x": 276,
                "y": 190
            },
            {
                "time": "12:40:17.308228",
                "x": 276,
                "y": 190
            },
            {
                "time": "12:40:47.321721",
                "x": 276,
                "y": 190
            },
            {
                "time": "12:41:17.331112",
                "x": 276,
                "y": 190
            }
        ],
        "2025-02-21": [
            {
                "time": "11:47:18.010926",
                "x": 389,
                "y": 364
            },
            {
                "time": "11:47:48.020597",
                "x": 389,
                "y": 364
            },
            {
                "time": "11:48:18.029811",
                "x": 389,
                "y": 364
            },
            {
                "time": "11:48:48.038732",
                "x": 389,
                "y": 364
            },
            {
                "time": "11:49:18.051971",
                "x": 389,
                "y": 364
            },
            {
                "time": "11:49:48.062220",
                "x": 389,
                "y": 364
            },
            {
                "time": "11:50:18.070096",
                "x": 389,
                "y": 364
            },
            {
                "time": "11:50:48.077690",
                "x": 389,
                "y": 364
            },
            {
                "time": "11:51:18.085698",
                "x": 389,
                "y": 364
            },
            {
                "time": "11:51:48.096998",
                "x": 389,
                "y": 364
            },
            {
                "time": "11:52:18.105372",
                "x": 389,
                "y": 364
            },
            {
                "time": "11:52:48.115901",
                "x": 389,
                "y": 364
            },
            {
                "time": "11:53:18.126106",
                "x": 389,
                "y": 364
            },
            {
                "time": "11:53:48.138838",
                "x": 389,
                "y": 364
            },
            {
                "time": "11:54:20.197906",
                "x": 389,
                "y": 364
            },
            {
                "time": "11:54:39.636820",
                "x": 270,
                "y": 172
            },
            {
                "time": "11:55:09.648482",
                "x": 270,
                "y": 172
            },
            {
                "time": "11:55:39.655627",
                "x": 270,
                "y": 172
            },
            {
                "time": "11:56:09.663323",
                "x": 270,
                "y": 172
            },
            {
                "time": "11:56:39.673285",
                "x": 270,
                "y": 172
            },
            {
                "time": "11:57:09.684108",
                "x": 270,
                "y": 172
            },
            {
                "time": "11:57:39.703884",
                "x": 270,
                "y": 172
            },
            {
                "time": "11:58:09.708273",
                "x": 270,
                "y": 172
            },
            {
                "time": "11:58:39.723410",
                "x": 270,
                "y": 172
            },
            {
                "time": "11:59:09.735636",
                "x": 270,
                "y": 172
            },
            {
                "time": "11:59:39.742420",
                "x": 270,
                "y": 172
            },
            {
                "time": "12:00:09.758894",
                "x": 270,
                "y": 172
            },
            {
                "time": "12:00:39.767391",
                "x": 270,
                "y": 172
            },
            {
                "time": "12:01:09.794542",
                "x": 270,
                "y": 172
            },
            {
                "time": "12:01:39.808289",
                "x": 270,
                "y": 172
            },
            {
                "time": "12:02:09.824764",
                "x": 270,
                "y": 172
            },
            {
                "time": "12:02:40.688416",
                "x": 270,
                "y": 172
            },
            {
                "time": "12:03:10.698894",
                "x": 270,
                "y": 172
            },
            {
                "time": "12:03:40.707884",
                "x": 270,
                "y": 172
            },
            {
                "time": "12:04:10.718459",
                "x": 270,
                "y": 172
            },
            {
                "time": "12:04:40.728890",
                "x": 270,
                "y": 172
            },
            {
                "time": "12:05:10.737847",
                "x": 270,
                "y": 172
            },
            {
                "time": "12:05:40.750369",
                "x": 270,
                "y": 172
            },
            {
                "time": "12:06:10.755108",
                "x": 270,
                "y": 172
            },
            {
                "time": "12:06:40.763331",
                "x": 270,
                "y": 172
            },
            {
                "time": "12:07:10.771923",
                "x": 270,
                "y": 172
            },
            {
                "time": "12:07:40.781311",
                "x": 270,
                "y": 172
            },
            {
                "time": "12:08:10.793231",
                "x": 270,
                "y": 172
            },
            {
                "time": "12:08:40.802557",
                "x": 270,
                "y": 172
            },
            {
                "time": "12:09:10.813332",
                "x": 270,
                "y": 172
            },
            {
                "time": "12:09:40.821597",
                "x": 270,
                "y": 172
            },
            {
                "time": "12:10:10.829778",
                "x": 270,
                "y": 172
            },
            {
                "time": "12:10:40.841105",
                "x": 270,
                "y": 172
            },
            {
                "time": "12:11:10.848505",
                "x": 270,
                "y": 172
            },
            {
                "time": "12:11:40.855923",
                "x": 270,
                "y": 172
            },
            {
                "time": "12:12:10.866651",
                "x": 270,
                "y": 172
            },
            {
                "time": "12:12:40.876355",
                "x": 270,
                "y": 172
            },
            {
                "time": "12:13:10.885502",
                "x": 270,
                "y": 172
            },
            {
                "time": "12:13:40.895505",
                "x": 270,
                "y": 172
            },
            {
                "time": "12:14:10.903111",
                "x": 270,
                "y": 172
            },
            {
                "time": "12:14:40.914480",
                "x": 270,
                "y": 172
            },
            {
                "time": "12:15:10.923168",
                "x": 270,
                "y": 172
            },
            {
                "time": "12:15:40.932182",
                "x": 270,
                "y": 172
            },
            {
                "time": "12:16:10.942091",
                "x": 270,
                "y": 172
            },
            {
                "time": "12:16:40.952915",
                "x": 270,
                "y": 172
            },
            {
                "time": "12:17:10.960243",
                "x": 270,
                "y": 172
            },
            {
                "time": "12:17:40.968557",
                "x": 270,
                "y": 172
            },
            {
                "time": "12:18:10.976469",
                "x": 270,
                "y": 172
            },
            {
                "time": "12:18:40.984916",
                "x": 270,
                "y": 172
            },
            {
                "time": "12:19:10.993377",
                "x": 270,
                "y": 172
            },
            {
                "time": "12:19:41.002543",
                "x": 270,
                "y": 172
            },
            {
                "time": "12:20:11.011247",
                "x": 270,
                "y": 172
            },
            {
                "time": "12:20:41.018134",
                "x": 270,
                "y": 172
            },
            {
                "time": "12:21:11.026635",
                "x": 270,
                "y": 172
            },
            {
                "time": "12:21:41.035938",
                "x": 270,
                "y": 172
            },
            {
                "time": "12:22:11.044808",
                "x": 270,
                "y": 172
            },
            {
                "time": "12:22:41.054430",
                "x": 270,
                "y": 172
            },
            {
                "time": "12:23:11.062048",
                "x": 270,
                "y": 172
            },
            {
                "time": "12:23:41.072802",
                "x": 270,
                "y": 172
            },
            {
                "time": "12:24:11.079461",
                "x": 270,
                "y": 172
            },
            {
                "time": "12:24:41.088930",
                "x": 270,
                "y": 172
            },
            {
                "time": "12:25:11.098233",
                "x": 270,
                "y": 172
            },
            {
                "time": "12:25:41.107067",
                "x": 270,
                "y": 172
            },
            {
                "time": "12:26:11.117110",
                "x": 270,
                "y": 172
            },
            {
                "time": "12:26:41.124908",
                "x": 270,
                "y": 172
            },
            {
                "time": "12:27:11.135255",
                "x": 270,
                "y": 172
            },
            {
                "time": "12:27:41.145453",
                "x": 270,
                "y": 172
            },
            {
                "time": "12:28:11.153802",
                "x": 270,
                "y": 172
            },
            {
                "time": "12:28:41.163523",
                "x": 270,
                "y": 172
            },
            {
                "time": "12:29:11.172068",
                "x": 270,
                "y": 172
            },
            {
                "time": "12:29:41.180824",
                "x": 270,
                "y": 172
            },
            {
                "time": "12:30:11.190931",
                "x": 270,
                "y": 172
            },
            {
                "time": "12:30:41.199390",
                "x": 270,
                "y": 172
            },
            {
                "time": "12:31:11.207354",
                "x": 270,
                "y": 172
            },
            {
                "time": "12:31:41.218899",
                "x": 270,
                "y": 172
            },
            {
                "time": "12:32:11.229005",
                "x": 270,
                "y": 172
            },
            {
                "time": "12:32:41.236266",
                "x": 270,
                "y": 172
            },
            {
                "time": "12:33:11.246142",
                "x": 270,
                "y": 172
            },
            {
                "time": "12:33:41.255270",
                "x": 270,
                "y": 172
            },
            {
                "time": "12:34:11.264760",
                "x": 270,
                "y": 172
            }
        ],
        "2025-02-27": [
            {
                "time": "22:34:37.680764",
                "x": 270,
                "y": 172
            },
            {
                "time": "22:35:07.692329",
                "x": 270,
                "y": 170
            },
            {
                "time": "22:35:37.704687",
                "x": 290,
                "y": 194
            },
            {
                "time": "22:36:07.705460",
                "x": 290,
                "y": 194
            },
            {
                "time": "22:36:37.717574",
                "x": 290,
                "y": 194
            },
            {
                "time": "22:37:07.721792",
                "x": 290,
                "y": 194
            },
            {
                "time": "22:37:37.731071",
                "x": 290,
                "y": 194
            },
            {
                "time": "22:38:07.740023",
                "x": 290,
                "y": 194
            },
            {
                "time": "22:38:37.749271",
                "x": 290,
                "y": 194
            },
            {
                "time": "22:39:07.757963",
                "x": 290,
                "y": 194
            },
            {
                "time": "22:59:47.101247",
                "x": 230,
                "y": 322
            },
            {
                "time": "23:00:17.107663",
                "x": 230,
                "y": 322
            },
            {
                "time": "23:00:47.114963",
                "x": 230,
                "y": 322
            },
            {
                "time": "23:01:17.123184",
                "x": 230,
                "y": 322
            },
            {
                "time": "23:01:47.132839",
                "x": 230,
                "y": 322
            },
            {
                "time": "23:02:17.141645",
                "x": 230,
                "y": 322
            },
            {
                "time": "23:02:47.151487",
                "x": 230,
                "y": 322
            },
            {
                "time": "23:03:17.160371",
                "x": 230,
                "y": 322
            },
            {
                "time": "23:03:56.172459",
                "x": 230,
                "y": 322
            },
            {
                "time": "23:04:26.180278",
                "x": 230,
                "y": 322
            },
            {
                "time": "23:04:56.188100",
                "x": 230,
                "y": 322
            },
            {
                "time": "23:05:26.196285",
                "x": 230,
                "y": 322
            },
            {
                "time": "23:05:56.206157",
                "x": 230,
                "y": 322
            },
            {
                "time": "23:06:26.213026",
                "x": 230,
                "y": 322
            },
            {
                "time": "23:06:56.222889",
                "x": 230,
                "y": 322
            },
            {
                "time": "23:07:26.231634",
                "x": 230,
                "y": 322
            },
            {
                "time": "23:07:56.239934",
                "x": 230,
                "y": 322
            },
            {
                "time": "23:08:26.249060",
                "x": 230,
                "y": 322
            },
            {
                "time": "23:08:56.255977",
                "x": 230,
                "y": 322
            },
            {
                "time": "23:09:26.265019",
                "x": 230,
                "y": 322
            },
            {
                "time": "23:09:56.273370",
                "x": 230,
                "y": 322
            },
            {
                "time": "23:10:26.281224",
                "x": 230,
                "y": 322
            },
            {
                "time": "23:10:56.290011",
                "x": 230,
                "y": 322
            },
            {
                "time": "23:11:26.297632",
                "x": 230,
                "y": 322
            },
            {
                "time": "23:11:56.305931",
                "x": 230,
                "y": 322
            },
            {
                "time": "23:12:26.314507",
                "x": 230,
                "y": 322
            },
            {
                "time": "23:12:56.321525",
                "x": 230,
                "y": 322
            },
            {
                "time": "23:13:26.330663",
                "x": 230,
                "y": 322
            },
            {
                "time": "23:13:56.339715",
                "x": 230,
                "y": 322
            },
            {
                "time": "23:14:26.347410",
                "x": 230,
                "y": 322
            },
            {
                "time": "23:14:56.353832",
                "x": 230,
                "y": 322
            },
            {
                "time": "23:15:26.363374",
                "x": 230,
                "y": 322
            },
            {
                "time": "23:15:56.371506",
                "x": 230,
                "y": 322
            },
            {
                "time": "23:16:26.379335",
                "x": 230,
                "y": 322
            },
            {
                "time": "23:16:56.388761",
                "x": 230,
                "y": 322
            },
            {
                "time": "23:17:26.395812",
                "x": 230,
                "y": 322
            },
            {
                "time": "23:17:56.404845",
                "x": 230,
                "y": 322
            },
            {
                "time": "23:18:26.412930",
                "x": 230,
                "y": 322
            },
            {
                "time": "23:18:56.420829",
                "x": 230,
                "y": 322
            },
            {
                "time": "23:19:26.429438",
                "x": 230,
                "y": 322
            },
            {
                "time": "23:19:56.437430",
                "x": 230,
                "y": 322
            },
            {
                "time": "23:20:26.447015",
                "x": 230,
                "y": 322
            },
            {
                "time": "23:28:23.645715",
                "x": 230,
                "y": 322
            },
            {
                "time": "23:28:53.655619",
                "x": 230,
                "y": 322
            },
            {
                "time": "23:29:23.662565",
                "x": 230,
                "y": 322
            },
            {
                "time": "23:29:53.670861",
                "x": 230,
                "y": 322
            },
            {
                "time": "23:30:23.678291",
                "x": 230,
                "y": 322
            },
            {
                "time": "23:30:53.686959",
                "x": 230,
                "y": 322
            },
            {
                "time": "23:31:23.696713",
                "x": 230,
                "y": 322
            },
            {
                "time": "23:31:53.704251",
                "x": 230,
                "y": 322
            },
            {
                "time": "23:32:23.713352",
                "x": 230,
                "y": 322
            },
            {
                "time": "23:32:53.720285",
                "x": 230,
                "y": 322
            },
            {
                "time": "23:33:23.727108",
                "x": 230,
                "y": 322
            },
            {
                "time": "23:33:53.735999",
                "x": 230,
                "y": 322
            },
            {
                "time": "23:34:23.743816",
                "x": 230,
                "y": 322
            },
            {
                "time": "23:34:53.752522",
                "x": 230,
                "y": 322
            },
            {
                "time": "23:35:23.760119",
                "x": 230,
                "y": 322
            },
            {
                "time": "23:35:53.767679",
                "x": 230,
                "y": 322
            },
            {
                "time": "23:36:23.776571",
                "x": 230,
                "y": 322
            },
            {
                "time": "23:36:53.785499",
                "x": 230,
                "y": 322
            },
            {
                "time": "23:37:23.792705",
                "x": 230,
                "y": 322
            },
            {
                "time": "23:37:53.802329",
                "x": 230,
                "y": 322
            },
            {
                "time": "23:38:23.810137",
                "x": 230,
                "y": 322
            },
            {
                "time": "23:38:53.817788",
                "x": 230,
                "y": 322
            },
            {
                "time": "23:39:23.827252",
                "x": 230,
                "y": 322
            },
            {
                "time": "23:39:53.836491",
                "x": 230,
                "y": 322
            },
            {
                "time": "23:40:23.843321",
                "x": 230,
                "y": 322
            },
            {
                "time": "23:40:53.852079",
                "x": 230,
                "y": 322
            },
            {
                "time": "23:41:23.859880",
                "x": 230,
                "y": 322
            },
            {
                "time": "23:41:53.868814",
                "x": 230,
                "y": 322
            },
            {
                "time": "23:42:23.877024",
                "x": 230,
                "y": 322
            },
            {
                "time": "23:42:53.887259",
                "x": 230,
                "y": 322
            },
            {
                "time": "23:43:23.895416",
                "x": 230,
                "y": 322
            },
            {
                "time": "23:43:53.903407",
                "x": 230,
                "y": 322
            },
            {
                "time": "23:44:23.911813",
                "x": 230,
                "y": 322
            },
            {
                "time": "23:44:53.921638",
                "x": 230,
                "y": 322
            },
            {
                "time": "23:45:23.929484",
                "x": 230,
                "y": 322
            },
            {
                "time": "23:45:53.939709",
                "x": 230,
                "y": 322
            },
            {
                "time": "23:46:23.945470",
                "x": 230,
                "y": 322
            },
            {
                "time": "23:46:53.953687",
                "x": 230,
                "y": 322
            },
            {
                "time": "23:47:23.961327",
                "x": 230,
                "y": 322
            },
            {
                "time": "23:47:53.969174",
                "x": 230,
                "y": 322
            },
            {
                "time": "23:48:23.976424",
                "x": 230,
                "y": 322
            },
            {
                "time": "23:48:53.986141",
                "x": 230,
                "y": 322
            },
            {
                "time": "23:49:23.996844",
                "x": 230,
                "y": 322
            },
            {
                "time": "23:49:54.005471",
                "x": 230,
                "y": 322
            },
            {
                "time": "23:50:24.014696",
                "x": 230,
                "y": 322
            },
            {
                "time": "23:50:54.023157",
                "x": 230,
                "y": 322
            },
            {
                "time": "23:51:24.030539",
                "x": 230,
                "y": 322
            },
            {
                "time": "23:51:54.040851",
                "x": 230,
                "y": 322
            },
            {
                "time": "23:52:24.050569",
                "x": 230,
                "y": 322
            },
            {
                "time": "23:52:54.057247",
                "x": 230,
                "y": 322
            },
            {
                "time": "23:53:24.066365",
                "x": 230,
                "y": 322
            },
            {
                "time": "23:53:54.073435",
                "x": 230,
                "y": 322
            },
            {
                "time": "23:54:24.084360",
                "x": 230,
                "y": 322
            },
            {
                "time": "23:54:54.096302",
                "x": 230,
                "y": 322
            }
        ],
        "2025-02-28": [
            {
                "time": "00:06:39.282137",
                "x": 230,
                "y": 322
            },
            {
                "time": "00:07:09.294172",
                "x": 230,
                "y": 322
            },
            {
                "time": "00:07:39.301831",
                "x": 230,
                "y": 322
            },
            {
                "time": "00:08:09.306918",
                "x": 230,
                "y": 322
            },
            {
                "time": "00:08:39.315689",
                "x": 230,
                "y": 322
            },
            {
                "time": "00:09:09.324786",
                "x": 230,
                "y": 322
            },
            {
                "time": "00:09:39.333296",
                "x": 230,
                "y": 322
            },
            {
                "time": "00:10:09.346552",
                "x": 230,
                "y": 322
            },
            {
                "time": "00:10:39.351038",
                "x": 230,
                "y": 322
            },
            {
                "time": "00:12:24.383842",
                "x": 230,
                "y": 322
            },
            {
                "time": "00:12:54.389877",
                "x": 230,
                "y": 322
            },
            {
                "time": "00:13:24.398874",
                "x": 230,
                "y": 322
            },
            {
                "time": "00:13:54.408255",
                "x": 230,
                "y": 322
            },
            {
                "time": "00:14:24.417558",
                "x": 230,
                "y": 322
            },
            {
                "time": "00:14:54.426173",
                "x": 230,
                "y": 322
            },
            {
                "time": "00:15:24.435957",
                "x": 230,
                "y": 322
            },
            {
                "time": "00:15:54.447613",
                "x": 230,
                "y": 322
            },
            {
                "time": "00:16:24.454969",
                "x": 230,
                "y": 322
            },
            {
                "time": "00:16:54.463814",
                "x": 230,
                "y": 322
            },
            {
                "time": "00:17:24.473197",
                "x": 230,
                "y": 322
            },
            {
                "time": "00:17:54.506895",
                "x": 230,
                "y": 322
            },
            {
                "time": "00:18:26.344437",
                "x": 230,
                "y": 322
            },
            {
                "time": "00:18:56.353944",
                "x": 230,
                "y": 322
            },
            {
                "time": "00:19:26.360719",
                "x": 230,
                "y": 322
            },
            {
                "time": "00:19:38.515435",
                "x": 401,
                "y": 370
            },
            {
                "time": "00:20:08.524019",
                "x": 401,
                "y": 370
            },
            {
                "time": "00:20:38.542121",
                "x": 401,
                "y": 370
            },
            {
                "time": "00:21:08.543291",
                "x": 401,
                "y": 370
            },
            {
                "time": "00:21:38.548524",
                "x": 401,
                "y": 370
            },
            {
                "time": "00:22:08.559105",
                "x": 401,
                "y": 370
            },
            {
                "time": "00:22:38.570721",
                "x": 401,
                "y": 370
            },
            {
                "time": "00:23:08.582822",
                "x": 401,
                "y": 370
            },
            {
                "time": "00:23:38.589563",
                "x": 401,
                "y": 370
            },
            {
                "time": "00:24:08.604056",
                "x": 401,
                "y": 370
            },
            {
                "time": "00:24:38.610862",
                "x": 401,
                "y": 370
            },
            {
                "time": "00:25:08.617302",
                "x": 401,
                "y": 370
            },
            {
                "time": "00:25:38.625718",
                "x": 401,
                "y": 370
            },
            {
                "time": "00:26:08.639053",
                "x": 401,
                "y": 370
            },
            {
                "time": "00:26:38.649533",
                "x": 401,
                "y": 370
            },
            {
                "time": "00:27:08.663647",
                "x": 401,
                "y": 370
            },
            {
                "time": "00:27:38.668492",
                "x": 401,
                "y": 370
            },
            {
                "time": "00:28:08.677493",
                "x": 401,
                "y": 370
            },
            {
                "time": "00:28:38.689720",
                "x": 401,
                "y": 370
            },
            {
                "time": "00:29:08.703108",
                "x": 401,
                "y": 370
            },
            {
                "time": "00:29:38.706304",
                "x": 401,
                "y": 370
            },
            {
                "time": "00:30:08.714494",
                "x": 401,
                "y": 370
            },
            {
                "time": "00:32:33.756269",
                "x": 230,
                "y": 322
            },
            {
                "time": "00:33:03.763373",
                "x": 230,
                "y": 322
            },
            {
                "time": "00:33:33.770560",
                "x": 230,
                "y": 322
            },
            {
                "time": "00:34:03.781068",
                "x": 230,
                "y": 322
            },
            {
                "time": "00:37:38.707409",
                "x": 353,
                "y": 190
            },
            {
                "time": "00:38:08.713523",
                "x": 353,
                "y": 190
            },
            {
                "time": "00:42:39.961558",
                "x": 230,
                "y": 322
            },
            {
                "time": "00:43:09.968690",
                "x": 230,
                "y": 322
            },
            {
                "time": "00:49:52.080313",
                "x": 230,
                "y": 322
            },
            {
                "time": "00:50:22.089964",
                "x": 230,
                "y": 322
            },
            {
                "time": "00:50:52.104572",
                "x": 230,
                "y": 322
            },
            {
                "time": "00:51:22.123879",
                "x": 230,
                "y": 322
            },
            {
                "time": "00:51:53.949357",
                "x": 230,
                "y": 322
            },
            {
                "time": "00:52:23.957151",
                "x": 230,
                "y": 322
            },
            {
                "time": "00:52:53.966353",
                "x": 230,
                "y": 322
            },
            {
                "time": "00:53:23.975197",
                "x": 230,
                "y": 322
            },
            {
                "time": "00:53:53.984349",
                "x": 230,
                "y": 322
            },
            {
                "time": "00:54:23.992590",
                "x": 230,
                "y": 322
            },
            {
                "time": "00:54:54.001210",
                "x": 230,
                "y": 322
            },
            {
                "time": "00:55:24.009328",
                "x": 230,
                "y": 322
            },
            {
                "time": "00:55:54.019477",
                "x": 230,
                "y": 322
            },
            {
                "time": "00:56:24.028424",
                "x": 230,
                "y": 322
            },
            {
                "time": "00:56:54.037329",
                "x": 230,
                "y": 322
            },
            {
                "time": "00:57:24.046923",
                "x": 230,
                "y": 322
            },
            {
                "time": "00:57:54.054784",
                "x": 230,
                "y": 322
            },
            {
                "time": "00:58:24.063400",
                "x": 230,
                "y": 322
            },
            {
                "time": "00:58:54.071203",
                "x": 230,
                "y": 322
            },
            {
                "time": "00:59:24.079578",
                "x": 230,
                "y": 322
            },
            {
                "time": "00:59:54.089687",
                "x": 230,
                "y": 322
            },
            {
                "time": "01:00:24.098301",
                "x": 230,
                "y": 322
            },
            {
                "time": "01:00:54.107428",
                "x": 230,
                "y": 322
            },
            {
                "time": "01:01:24.114024",
                "x": 230,
                "y": 322
            },
            {
                "time": "01:01:54.122203",
                "x": 230,
                "y": 322
            },
            {
                "time": "01:02:24.128615",
                "x": 230,
                "y": 322
            },
            {
                "time": "01:10:57.411875",
                "x": 401,
                "y": 370
            },
            {
                "time": "01:11:27.420954",
                "x": 401,
                "y": 370
            },
            {
                "time": "01:11:57.429546",
                "x": 401,
                "y": 370
            },
            {
                "time": "01:12:27.439037",
                "x": 401,
                "y": 370
            },
            {
                "time": "01:12:57.446741",
                "x": 401,
                "y": 370
            },
            {
                "time": "01:13:27.454952",
                "x": 401,
                "y": 370
            },
            {
                "time": "01:13:57.466837",
                "x": 401,
                "y": 370
            },
            {
                "time": "01:14:55.915337",
                "x": 230,
                "y": 322
            },
            {
                "time": "01:15:27.366623",
                "x": 230,
                "y": 322
            },
            {
                "time": "01:15:57.378111",
                "x": 230,
                "y": 322
            },
            {
                "time": "01:16:36.509569",
                "x": 401,
                "y": 370
            },
            {
                "time": "01:17:06.523374",
                "x": 401,
                "y": 370
            },
            {
                "time": "01:17:36.531016",
                "x": 401,
                "y": 370
            },
            {
                "time": "01:19:30.557625",
                "x": 401,
                "y": 370
            },
            {
                "time": "01:20:04.608783",
                "x": 230,
                "y": 322
            },
            {
                "time": "01:20:34.621226",
                "x": 230,
                "y": 322
            },
            {
                "time": "01:21:04.631539",
                "x": 230,
                "y": 322
            },
            {
                "time": "01:21:34.637409",
                "x": 230,
                "y": 322
            },
            {
                "time": "01:22:04.643072",
                "x": 230,
                "y": 322
            },
            {
                "time": "01:22:34.653877",
                "x": 230,
                "y": 322
            },
            {
                "time": "01:23:12.621680",
                "x": 401,
                "y": 370
            },
            {
                "time": "01:23:55.673965",
                "x": 230,
                "y": 322
            },
            {
                "time": "01:24:25.680716",
                "x": 230,
                "y": 322
            },
            {
                "time": "01:24:55.689772",
                "x": 230,
                "y": 322
            },
            {
                "time": "01:25:25.704384",
                "x": 230,
                "y": 322
            },
            {
                "time": "01:25:55.706421",
                "x": 230,
                "y": 322
            },
            {
                "time": "01:26:25.716474",
                "x": 230,
                "y": 322
            },
            {
                "time": "01:26:43.721383",
                "x": 230,
                "y": 322
            },
            {
                "time": "01:27:13.732183",
                "x": 230,
                "y": 322
            },
            {
                "time": "01:30:36.746808",
                "x": 401,
                "y": 370
            },
            {
                "time": "11:44:01.836827",
                "x": 353,
                "y": 190
            },
            {
                "time": "11:44:31.844707",
                "x": 353,
                "y": 190
            },
            {
                "time": "11:45:01.864462",
                "x": 353,
                "y": 190
            },
            {
                "time": "11:45:31.973226",
                "x": 353,
                "y": 190
            },
            {
                "time": "11:46:01.983243",
                "x": 353,
                "y": 190
            },
            {
                "time": "11:56:39.603372",
                "x": 230,
                "y": 322
            },
            {
                "time": "11:57:11.075900",
                "x": 230,
                "y": 322
            },
            {
                "time": "11:57:41.187029",
                "x": 230,
                "y": 322
            },
            {
                "time": "11:58:11.197543",
                "x": 230,
                "y": 322
            },
            {
                "time": "11:58:41.205202",
                "x": 230,
                "y": 322
            },
            {
                "time": "11:59:11.215364",
                "x": 230,
                "y": 322
            },
            {
                "time": "11:59:41.223692",
                "x": 230,
                "y": 322
            },
            {
                "time": "12:00:11.233379",
                "x": 230,
                "y": 322
            },
            {
                "time": "12:00:41.244501",
                "x": 230,
                "y": 322
            },
            {
                "time": "12:01:11.252656",
                "x": 230,
                "y": 322
            },
            {
                "time": "12:01:41.260332",
                "x": 230,
                "y": 322
            },
            {
                "time": "12:02:11.271364",
                "x": 230,
                "y": 322
            },
            {
                "time": "12:02:41.278522",
                "x": 230,
                "y": 322
            },
            {
                "time": "12:03:11.290252",
                "x": 230,
                "y": 322
            },
            {
                "time": "12:03:41.300308",
                "x": 230,
                "y": 322
            },
            {
                "time": "12:04:11.308834",
                "x": 230,
                "y": 322
            },
            {
                "time": "12:04:41.318864",
                "x": 230,
                "y": 322
            },
            {
                "time": "12:05:11.326862",
                "x": 230,
                "y": 322
            },
            {
                "time": "12:05:41.335621",
                "x": 230,
                "y": 322
            },
            {
                "time": "12:06:11.344955",
                "x": 230,
                "y": 322
            },
            {
                "time": "12:06:41.355519",
                "x": 230,
                "y": 322
            },
            {
                "time": "12:07:11.364119",
                "x": 230,
                "y": 322
            },
            {
                "time": "12:07:41.373110",
                "x": 230,
                "y": 322
            },
            {
                "time": "12:08:11.382754",
                "x": 230,
                "y": 322
            },
            {
                "time": "12:08:41.393235",
                "x": 230,
                "y": 322
            },
            {
                "time": "12:09:03.464527",
                "x": 230,
                "y": 322
            },
            {
                "time": "12:09:33.472133",
                "x": 230,
                "y": 322
            },
            {
                "time": "12:13:08.474053",
                "x": 401,
                "y": 370
            },
            {
                "time": "12:13:38.486824",
                "x": 401,
                "y": 370
            },
            {
                "time": "12:14:08.489893",
                "x": 401,
                "y": 370
            },
            {
                "time": "12:14:38.499409",
                "x": 401,
                "y": 370
            },
            {
                "time": "12:15:08.510287",
                "x": 401,
                "y": 370
            },
            {
                "time": "12:16:35.410419",
                "x": 353,
                "y": 190
            },
            {
                "time": "12:17:05.420238",
                "x": 353,
                "y": 190
            },
            {
                "time": "12:17:35.439048",
                "x": 353,
                "y": 190
            },
            {
                "time": "12:18:05.551520",
                "x": 353,
                "y": 190
            },
            {
                "time": "12:18:51.635742",
                "x": 230,
                "y": 322
            },
            {
                "time": "12:19:21.647255",
                "x": 230,
                "y": 322
            },
            {
                "time": "12:19:51.663100",
                "x": 230,
                "y": 322
            },
            {
                "time": "12:20:21.663673",
                "x": 230,
                "y": 322
            },
            {
                "time": "12:20:40.017305",
                "x": 230,
                "y": 322
            },
            {
                "time": "12:21:11.491518",
                "x": 230,
                "y": 322
            },
            {
                "time": "12:22:51.707863",
                "x": 230,
                "y": 322
            },
            {
                "time": "12:23:12.712647",
                "x": 230,
                "y": 322
            },
            {
                "time": "12:23:39.719639",
                "x": 230,
                "y": 322
            },
            {
                "time": "12:24:11.657678",
                "x": 401,
                "y": 370
            },
            {
                "time": "12:24:44.667002",
                "x": 401,
                "y": 370
            },
            {
                "time": "12:25:23.689537",
                "x": 401,
                "y": 370
            },
            {
                "time": "12:25:54.747373",
                "x": 401,
                "y": 370
            },
            {
                "time": "12:26:24.756710",
                "x": 401,
                "y": 370
            },
            {
                "time": "12:34:44.836430",
                "x": 401,
                "y": 370
            },
            {
                "time": "12:35:14.840463",
                "x": 401,
                "y": 370
            },
            {
                "time": "12:35:44.865553",
                "x": 401,
                "y": 370
            },
            {
                "time": "12:36:14.874729",
                "x": 401,
                "y": 370
            },
            {
                "time": "12:36:45.934633",
                "x": 401,
                "y": 370
            },
            {
                "time": "12:37:27.964218",
                "x": 230,
                "y": 322
            },
            {
                "time": "12:38:38.898677",
                "x": 401,
                "y": 370
            },
            {
                "time": "12:39:49.338143",
                "x": 230,
                "y": 322
            },
            {
                "time": "12:40:20.812373",
                "x": 230,
                "y": 322
            },
            {
                "time": "12:40:50.817979",
                "x": 230,
                "y": 322
            },
            {
                "time": "12:41:20.827997",
                "x": 230,
                "y": 322
            },
            {
                "time": "12:41:58.031565",
                "x": 230,
                "y": 322
            }
        ]
    }
}